oguild/__init__.py
oguild/log/__init__.py
oguild/logs/README.md
oguild/logs/__init__.py
oguild/logs/logger.py
oguild/middleware/README.md
oguild/middleware/__init__.py
oguild/middleware/error_middleware.py
oguild/middlewares/__init__.py
oguild/response/README.md
oguild/response/__init__.py
oguild/response/errors/__init__.py
oguild/response/errors/authentication_errors.py
oguild/response/errors/common_errors.py
oguild/response/errors/database_errors.py
oguild/response/errors/file_errors.py
oguild/response/errors/network_errors.py
oguild/response/errors/validation_errors.py
oguild/response/response.py
oguild/responses/__init__.py
oguild/utils/README.md
oguild/utils/__init__.py
oguild/utils/case_converter.py
oguild/utils/decoder.py
oguild/utils/encoder.py
oguild/utils/sanitizer.py
oguild-0.1.14.dist-info/LICENSE
oguild-0.1.14.dist-info/METADATA
oguild-0.1.14.dist-info/WHEEL
oguild-0.1.14.dist-info/RECORD
