Metadata-Version: 2.1
Name: oguild
Version: 0.1.14
Summary: OGuild utilities — reusable logging and helpers for Python projects
Home-page: https://github.com/OpsGuild/guildpack
License: MIT
Keywords: utilities,oguild,helpers,python,opsguild,logging
Author: Hordunlarmy
Author-email: Hordunlarmy@gmail.com
Requires-Python: >=3.9
Classifier: Development Status :: 5 - Production/Stable
Classifier: Intended Audience :: Developers
Classifier: License :: OSI Approved :: MIT License
Classifier: Programming Language :: Python
Classifier: Programming Language :: Python :: 3
Classifier: Programming Language :: Python :: 3.9
Classifier: Programming Language :: Python :: 3.10
Classifier: Programming Language :: Python :: 3.11
Classifier: Programming Language :: Python :: 3.12
Classifier: Programming Language :: Python :: 3.13
Classifier: Programming Language :: Python :: 3.8
Provides-Extra: logstash
Requires-Dist: pydantic (>=2.0.0,<3.0.0)
Project-URL: Documentation, https://github.com/OpsGuild/guildpack#readme
Project-URL: Repository, https://github.com/OpsGuild/guildpack
